.coveragerc
.testr.conf
.travis.yml
AUTHORS
ChangeLog
LICENSE
README.md
requirements.txt
setup.cfg
setup.py
test-requirements.txt
tox.ini
keystoneauth_oidc_refreshtoken/__init__.py
keystoneauth_oidc_refreshtoken/exceptions.py
keystoneauth_oidc_refreshtoken/loading.py
keystoneauth_oidc_refreshtoken/plugin.py
keystoneauth_oidc_refreshtoken.egg-info/PKG-INFO
keystoneauth_oidc_refreshtoken.egg-info/SOURCES.txt
keystoneauth_oidc_refreshtoken.egg-info/dependency_links.txt
keystoneauth_oidc_refreshtoken.egg-info/entry_points.txt
keystoneauth_oidc_refreshtoken.egg-info/not-zip-safe
keystoneauth_oidc_refreshtoken.egg-info/pbr.json
keystoneauth_oidc_refreshtoken.egg-info/requires.txt
keystoneauth_oidc_refreshtoken.egg-info/top_level.txt
keystoneauth_oidc_refreshtoken/tests/__init__.py
keystoneauth_oidc_refreshtoken/tests/unit/__init__.py
keystoneauth_oidc_refreshtoken/tests/unit/oidc_fixtures.py
keystoneauth_oidc_refreshtoken/tests/unit/test_loading.py
keystoneauth_oidc_refreshtoken/tests/unit/test_oidc.py