Metadata-Version: 1.1
Name: keystoneauth-oidc-refreshtoken
Version: 0.1.0
Summary: OpenID Connect Access Token Procurement Through Refresh Token for OpenStack client
Home-page: https://github.com/quinoescobar/keystoneauth-oidc-refreshtoken
Author: Jose Joaquin Escobar Gomez
Author-email: alu0100837094@ull.edu.es
License: UNKNOWN
Platform: UNKNOWN
Classifier: Environment :: Console
Classifier: Environment :: OpenStack
Classifier: Intended Audience :: Information Technology
Classifier: Intended Audience :: System Administrators
Classifier: License :: OSI Approved :: Apache Software License
Classifier: Operating System :: POSIX :: Linux
Classifier: Programming Language :: Python
Classifier: Programming Language :: Python :: 2
Classifier: Programming Language :: Python :: 2.7
Classifier: Programming Language :: Python :: 3
Classifier: Programming Language :: Python :: 3.4
Classifier: Programming Language :: Python :: 3.5
